LICENSE
MANIFEST.in
README.md
setup.py
django_lazy_admin.egg-info/PKG-INFO
django_lazy_admin.egg-info/SOURCES.txt
django_lazy_admin.egg-info/dependency_links.txt
django_lazy_admin.egg-info/not-zip-safe
django_lazy_admin.egg-info/requires.txt
django_lazy_admin.egg-info/top_level.txt
lazy_admin/__init__.py
lazy_admin/decorators.py
lazy_admin/models.py
lazy_admin/urls.py
lazy_admin/views.py
lazy_admin/static/lazy/js/lazy_column.js
lazy_admin/templates/lazy_admin/change_list.html
lazy_admin/templates/lazy_admin/lazy_column.html