Metadata-Version: 1.1
Name: django-lazy-admin
Version: 1.0.1
Summary: Enhancement for custom columns in django admin list screens
Home-page: https://github.com/gkachru/django_lazy_admin
Author: Gautam Kachru
Author-email: gautam@live.in
License: BSD License
Platform: UNKNOWN
Classifier: Development Status :: 4 - Beta
Classifier: Environment :: Web Environment
Classifier: Framework :: Django
Classifier: Intended Audience :: Developers
Classifier: License :: OSI Approved :: BSD License
Classifier: Operating System :: OS Independent
Classifier: Programming Language :: Python
Classifier: Topic :: Software Development :: Libraries :: Python Modules
